{
  "jar_names": [
    "servercore-1.0.0.jar"
  ],
  "java_version": 17,
  "loader": "fabric",
  "log_relpath": "build.log",
  "metadata": {
    "authors": [
      "Itamio"
    ],
    "description": "Teleport requests, homes, random teleport, and first-join teleport without requiring cheats.",
    "entrypoint_class": "com.itamio.servercore.fabric.ServerCoreFabricMod",
    "group": "com.itamio",
    "homepage": null,
    "issues": null,
    "license": "All Rights Reserved",
    "mod_id": "servercore",
    "mod_version": "1.0.0",
    "name": "ServerCore",
    "runtime_side": "server",
    "sources": null
  },
  "minecraft_version": "1.19.3",
  "range_folder": "1.19-1.19.4",
  "requested_version_spec": "1.19-1.19.4",
  "slug": "servercore-fabric-1-19-3",
  "status": "success",
  "warnings": [
    "Template dependency versions are still anchored to 1.19.4 for this loader; update version-manifest.json before production use."
  ]
}
