{
  "version_number": "1.0.0",
  "version_title": "Auto Eat 1.0.0",
  "changelog": "Initial release:\n- Automatically eats food when hunger drops below configurable threshold (default: 14/20)\n- Smart food selection based on saturation values\n- Configurable food blacklist (spider eyes, rotten flesh, poisonous potatoes, golden apples, chorus fruit)\n- Minimal performance impact (checks once per second)\n- Works with any food item in inventory",
  "game_versions": ["1.12.2"],
  "loaders": ["forge"],
  "featured": true
}
