{
  "game_versions": [
    "1.21.6"
  ],
  "loaders": [
    "forge"
  ],
  "id": "nRvzrdN9",
  "project_id": "TvVDvfA5",
  "author_id": "JeqWCbnW",
  "featured": false,
  "name": "Set Home 1.0.0 (forge 1.21.6)",
  "version_number": "1.0.0",
  "changelog": "Automated upload from ModCompiler GitHub Actions.\n\nMod: Set Home\nMod version: 1.0.0\nLoader: forge\nMinecraft version: 1.21.6\nBuilt artifact: sethome-1.0.0.jar",
  "changelog_url": null,
  "date_published": "2026-03-15T04:48:44.869846Z",
  "downloads": 6,
  "version_type": "release",
  "status": "listed",
  "requested_status": null,
  "files": [
    {
      "id": "ndYNlo5L",
      "hashes": {
        "sha1": "31b73f1919507f4650480b56a02383c86dfb4354",
        "sha512": "376a7c085a06e4e6156afaaa2fbb58c0b304985159fe19129ef9396cd1e3df2c19f815e9a646f03e01ac0b6591d148dc7f2fe42ab5e5464b4e89d4713771dc50"
      },
      "url": "https://cdn.modrinth.com/data/TvVDvfA5/versions/nRvzrdN9/sethome-1.0.0.jar",
      "filename": "sethome-1.0.0.jar",
      "primary": true,
      "size": 1119,
      "file_type": null
    }
  ],
  "dependencies": []
}