{
  "description_image_url": "https://raw.githubusercontent.com/Sekai0NI0itamio/auto-crystal/main/.modcompiler-art/description-image.webp",
  "description_image_urls": [
    "https://raw.githubusercontent.com/Sekai0NI0itamio/auto-crystal/main/.modcompiler-art/description-image.webp"
  ],
  "generated_at": "2026-04-09T11:09:37+00:00",
  "last_error": "",
  "project_created_by_modcompiler": true,
  "project_id": "ijhHAT7f",
  "project_slug": "world-auto-crystal",
  "project_url": "https://modrinth.com/mod/world-auto-crystal",
  "status": "draft_created",
  "verified": true,
  "version_id": "Lreo0ZnH",
  "version_url": "https://modrinth.com/mod/world-auto-crystal/version/Lreo0ZnH",
  "warnings": []
}
